GNscraper.py
GNscraper-0.0.1.dist-info/LICENSE.txt
GNscraper-0.0.1.dist-info/METADATA
GNscraper-0.0.1.dist-info/WHEEL
GNscraper-0.0.1.dist-info/top_level.txt
GNscraper-0.0.1.dist-info/RECORD
