Metadata-Version: 2.1
Name: GNscraper
Version: 0.0.1
Summary: GNscraper stands for Google News Scraper which scrape News Articles from Google News based on given Keywords and returns Data Frame which contains Publishers, Title, Url, Uploaded Date and Uploaded DateTime of News Articles.
Home-page: https://github.com/mugilanD98/GNscraper
Author: Mugilan Deiveegan
License: UNKNOWN
Keywords: dynamic scraper,news scraping,gnews,google news,google news scraper,web scraping,GNscraper,web,news,live-scraper
Platform: UNKNOWN
Classifier: Programming Language :: Python :: 3
Classifier: License :: OSI Approved :: MIT License
Classifier: Operating System :: OS Independent
Requires-Python: >=3.7
License-File: LICENSE.txt
Requires-Dist: beautifulsoup4
Requires-Dist: requests
Requires-Dist: pandas
Requires-Dist: lxml
